snowland/__init__.py
snowland/database_tool/__init__.py
snowland/database_tool/mysql_tool/__init__.py
snowland/database_tool/mysql_tool/connection.py
snowland/database_tool/postgis_tool/__init__.py
snowland/database_tool/postgis_tool/connection.py
snowland/gis_tool/__init__.py
snowland/gis_tool/gis_helper.py
snowland/gis_tool/haversine.py
snowland/gis_tool/nds.py
snowland/gis_tool/transformer.py
snowland/gis_tool/pcl_tool/__init__.py
snowland/gis_tool/qgis_tool/__init__.py
snowland/gis_tool/qgis_tool/core.py
snowland/gis_tool/qgis_tool/distance_area.py
snowland/gis_tool/qgis_tool/qgis_util.py
snowland/gis_tool/qgis_tool/utils.py
snowland/gis_tool/qgis_tool/data_stucture/__init__.py
snowland/graphics/__init__.py
snowland/graphics/utils.py
snowland/graphics/core/__init__.py
snowland/graphics/core/analytic_geometry_2d.py
snowland/graphics/core/analytic_geometry_3d.py
snowland/graphics/core/analytic_geometry_base.py
snowland/graphics/core/computational_geometry_2d.py
snowland/graphics/core/computational_geometry_3d.py
snowland/graphics/core/computational_geometry_base.py
snowland/graphics/solid_geometry/__init__.py
snowland/graphics/solid_geometry/_ploygon.py
snowland/image/__init__.py
snowland/image/api/__init__.py
snowland/image/api/digital_screening.py
snowland/image/api/img_to_cartoon.py
snowland/image/api/img_to_freehand.py
snowland/image/api/img_to_oilpaint.py
snowland/image/api/img_to_sketch.py
snowland/image/color/__init__.py
snowland/image/color/_convert.py
snowland/image/color/color.py
snowland/image/core/__init__.py
snowland/image/exposure/__init__.py
snowland/image/exposure/exposure.py
snowland/image/measure/__init__.py
snowland/image/measure/measure.py
snowland/image/segmentation/__init__.py
snowland/image/segmentation/segmentation.py
snowland/image/style_migration/__init__.py
snowland/image/style_migration/img_to_cartoon.py
snowland/image/style_migration/img_to_freehand.py
snowland/image/style_migration/img_to_oilpaint.py
snowland_image-0.1.5.post1.dist-info/LICENSE
snowland_image-0.1.5.post1.dist-info/METADATA
snowland_image-0.1.5.post1.dist-info/WHEEL
snowland_image-0.1.5.post1.dist-info/top_level.txt
snowland_image-0.1.5.post1.dist-info/RECORD
