Metadata-Version: 2.1
Name: snowland-image
Version: 0.1.5.post1
Summary: toolkit for image
Home-page: https://github.com/AAFun/scikit-snowland
Author: A.Star
Author-email: astar@snowland.ltd
Maintainer: A.Star
Maintainer-email: astar@snowland.ltd
License: BSD License
Platform: all
Classifier: Development Status :: 4 - Beta
Classifier: Operating System :: OS Independent
Classifier: Intended Audience :: Developers
Classifier: License :: OSI Approved :: BSD License
Classifier: Programming Language :: Python
Classifier: Programming Language :: Python :: Implementation
Classifier: Programming Language :: Python :: 3
Classifier: Programming Language :: Python :: 3.6
Classifier: Programming Language :: Python :: 3.7
Classifier: Programming Language :: Python :: 3.8
Classifier: Programming Language :: Python :: 3.9
Classifier: Programming Language :: Python :: 3.10
Classifier: Topic :: Software Development :: Libraries
License-File: LICENSE
Requires-Dist: opencv-python>=3.4.1.15
Requires-Dist: numpy>=1.0.0
Requires-Dist: scipy>=1.0.0
Requires-Dist: matplotlib>=2.1.2
Requires-Dist: snowland-pencildraw>=0.1.7
Requires-Dist: astartool>=0.1.0
Provides-Extra: database_tool
Requires-Dist: psycopg2>=2.0.0; extra == "database-tool"
Requires-Dist: pymysql; extra == "database-tool"
Provides-Extra: gis_tool
Requires-Dist: GDAL>=3.1.0; extra == "gis-tool"
Requires-Dist: Pillow>=5.2.0; extra == "gis-tool"
Requires-Dist: pyproj>=2.6.0; extra == "gis-tool"
